[  
   {  
      "model":"blog.post",
      "pk":1,
      "fields":{  
         "title":"Hello World!",
         "author":"Jonathan Lowe",
         "date_published":"2017-01-18T19:41:59.757Z",
         "content":"<p>Hello world!</p>\r\n<p>I have decided to make a web comic, for my own personal enjoyment and so I would have a reason to learn about building websites.</p>\r\n<p>I have posted some comics I drew a while ago and will add more eventually; I will be busy for the next few months.</p>\r\n<p>This blog will be primarially used for posting updates and information about the comic.</p>\r\n<p>Adios amigos!</p>"
      }
   }  
]